odoo/addons/spec_driven_model/README.rst
odoo/addons/spec_driven_model/__init__.py
odoo/addons/spec_driven_model/__manifest__.py
odoo/addons/spec_driven_model/i18n/pt_BR.po
odoo/addons/spec_driven_model/i18n/spec_driven_model.pot
odoo/addons/spec_driven_model/models/__init__.py
odoo/addons/spec_driven_model/models/spec_export.py
odoo/addons/spec_driven_model/models/spec_import.py
odoo/addons/spec_driven_model/models/spec_mixin.py
odoo/addons/spec_driven_model/models/spec_models.py
odoo/addons/spec_driven_model/models/spec_view.py
odoo/addons/spec_driven_model/readme/CONFIGURE.md
odoo/addons/spec_driven_model/readme/CONTRIBUTORS.md
odoo/addons/spec_driven_model/readme/DESCRIPTION.md
odoo/addons/spec_driven_model/readme/HISTORY.md
odoo/addons/spec_driven_model/readme/INSTALL.md
odoo/addons/spec_driven_model/readme/ROADMAP.md
odoo/addons/spec_driven_model/readme/USAGE.md
odoo/addons/spec_driven_model/static/description/icon.png
odoo/addons/spec_driven_model/static/description/index.html
odoo/addons/spec_driven_model/tests/PurchaseOrderSchema.xsd
odoo/addons/spec_driven_model/tests/__init__.py
odoo/addons/spec_driven_model/tests/fake_mixin.py
odoo/addons/spec_driven_model/tests/fake_odoo_purchase.py
odoo/addons/spec_driven_model/tests/purchase_order_lib.py
odoo/addons/spec_driven_model/tests/spec_poxsd.py
odoo/addons/spec_driven_model/tests/spec_purchase.py
odoo/addons/spec_driven_model/tests/test_spec_model.py
odoo_addon_spec_driven_model-18.0.1.1.1.dist-info/METADATA
odoo_addon_spec_driven_model-18.0.1.1.1.dist-info/WHEEL
odoo_addon_spec_driven_model-18.0.1.1.1.dist-info/top_level.txt
odoo_addon_spec_driven_model-18.0.1.1.1.dist-info/RECORD
