Metadata-Version: 2.1
Name: odoo-addon-spec_driven_model
Version: 18.0.1.1.1
Requires-Python: >=3.10
Requires-Dist: odoo==18.0.*
Summary: XML binding for Odoo: XML to Odoo models and models to XML.
Home-page: https://github.com/OCA/l10n-brazil
License: LGPL-3
Author: Akretion, Odoo Community Association (OCA)
Author-email: support@odoo-community.org
Classifier: Programming Language :: Python
Classifier: Framework :: Odoo
Classifier: Framework :: Odoo :: 18.0
Classifier: License :: OSI Approved :: GNU Lesser General Public License v3 (LGPLv3)
Classifier: Development Status :: 4 - Beta
